{"Id":3164603,"JSON-DATI ":[{"Main":{"Speed":2.07,"Feels_Like":273.73,"Temp":275.82,"Temp_max":278.64,"Temp_min":275.82,"Data":"2022-01-20 21:00:00"}},{"Main":{"Speed":1.8,"Feels_Like":274.85,"Temp":276.52,"Temp_max":277.93,"Temp_min":276.52,"Data":"2022-01-21 00:00:00"}},{"Main":{"Speed":2.85,"Feels_Like":274.18,"Temp":276.82,"Temp_max":277.32,"Temp_min":276.82,"Data":"2022-01-21 03:00:00"}},{"Main":{"Speed":5.19,"Feels_Like":272.8,"Temp":276.88,"Temp_max":276.88,"Temp_min":276.88,"Data":"2022-01-21 06:00:00"}},{"Main":{"Speed":6.25,"Feels_Like":274.31,"Temp":278.44,"Temp_max":278.44,"Temp_min":278.44,"Data":"2022-01-21 09:00:00"}},{"Main":{"Speed":5.86,"Feels_Like":276.87,"Temp":280.33,"Temp_max":280.33,"Temp_min":280.33,"Data":"2022-01-21 12:00:00"}},{"Main":{"Speed":2.97,"Feels_Like":277.85,"Temp":279.96,"Temp_max":279.96,"Temp_min":279.96,"Data":"2022-01-21 15:00:00"}},{"Main":{"Speed":2.61,"Feels_Like":276.22,"Temp":278.37,"Temp_max":278.37,"Temp_min":278.37,"Data":"2022-01-21 18:00:00"}},{"Main":{"Speed":2.15,"Feels_Like":275.33,"Temp":277.26,"Temp_max":277.26,"Temp_min":277.26,"Data":"2022-01-21 21:00:00"}},{"Main":{"Speed":1.67,"Feels_Like":275.13,"Temp":276.62,"Temp_max":276.62,"Temp_min":276.62,"Data":"2022-01-22 00:00:00"}},{"Main":{"Speed":2.05,"Feels_Like":273.64,"Temp":275.73,"Temp_max":275.73,"Temp_min":275.73,"Data":"2022-01-22 03:00:00"}},{"Main":{"Speed":1.37,"Feels_Like":274.01,"Temp":275.27,"Temp_max":275.27,"Temp_min":275.27,"Data":"2022-01-22 06:00:00"}},{"Main":{"Speed":3.11,"Feels_Like":274.07,"Temp":276.9,"Temp_max":276.9,"Temp_min":276.9,"Data":"2022-01-22 09:00:00"}},{"Main":{"Speed":3.24,"Feels_Like":276.52,"Temp":279.01,"Temp_max":279.01,"Temp_min":279.01,"Data":"2022-01-22 12:00:00"}},{"Main":{"Speed":1.12,"Feels_Like":279.08,"Temp":279.08,"Temp_max":279.08,"Temp_min":279.08,"Data":"2022-01-22 15:00:00"}},{"Main":{"Speed":1.76,"Feels_Like":275.91,"Temp":277.4,"Temp_max":277.4,"Temp_min":277.4,"Data":"2022-01-22 18:00:00"}},{"Main":{"Speed":2.1,"Feels_Like":274.8,"Temp":276.77,"Temp_max":276.77,"Temp_min":276.77,"Data":"2022-01-22 21:00:00"}},{"Main":{"Speed":2.36,"Feels_Like":273.85,"Temp":276.18,"Temp_max":276.18,"Temp_min":276.18,"Data":"2022-01-23 00:00:00"}},{"Main":{"Speed":1.98,"Feels_Like":273.86,"Temp":275.85,"Temp_max":275.85,"Temp_min":275.85,"Data":"2022-01-23 03:00:00"}},{"Main":{"Speed":1.99,"Feels_Like":273.86,"Temp":275.86,"Temp_max":275.86,"Temp_min":275.86,"Data":"2022-01-23 06:00:00"}},{"Main":{"Speed":1.67,"Feels_Like":275.75,"Temp":277.16,"Temp_max":277.16,"Temp_min":277.16,"Data":"2022-01-23 09:00:00"}},{"Main":{"Speed":0.67,"Feels_Like":279.29,"Temp":279.29,"Temp_max":279.29,"Temp_min":279.29,"Data":"2022-01-23 12:00:00"}},{"Main":{"Speed":0.63,"Feels_Like":279.54,"Temp":279.54,"Temp_max":279.54,"Temp_min":279.54,"Data":"2022-01-23 15:00:00"}},{"Main":{"Speed":1.51,"Feels_Like":277.05,"Temp":278.12,"Temp_max":278.12,"Temp_min":278.12,"Data":"2022-01-23 18:00:00"}},{"Main":{"Speed":1.83,"Feels_Like":275.97,"Temp":277.52,"Temp_max":277.52,"Temp_min":277.52,"Data":"2022-01-23 21:00:00"}},{"Main":{"Speed":1.35,"Feels_Like":276.22,"Temp":277.19,"Temp_max":277.19,"Temp_min":277.19,"Data":"2022-01-24 00:00:00"}},{"Main":{"Speed":1.55,"Feels_Like":275.61,"Temp":276.91,"Temp_max":276.91,"Temp_min":276.91,"Data":"2022-01-24 03:00:00"}},{"Main":{"Speed":2.45,"Feels_Like":274.01,"Temp":276.39,"Temp_max":276.39,"Temp_min":276.39,"Data":"2022-01-24 06:00:00"}},{"Main":{"Speed":2.38,"Feels_Like":275.8,"Temp":277.85,"Temp_max":277.85,"Temp_min":277.85,"Data":"2022-01-24 09:00:00"}},{"Main":{"Speed":1.47,"Feels_Like":279.39,"Temp":280.13,"Temp_max":280.13,"Temp_min":280.13,"Data":"2022-01-24 12:00:00"}},{"Main":{"Speed":0.54,"Feels_Like":280.38,"Temp":280.38,"Temp_max":280.38,"Temp_min":280.38,"Data":"2022-01-24 15:00:00"}},{"Main":{"Speed":0.23,"Feels_Like":279.86,"Temp":279.86,"Temp_max":279.86,"Temp_min":279.86,"Data":"2022-01-24 18:00:00"}},{"Main":{"Speed":1.18,"Feels_Like":279.41,"Temp":279.41,"Temp_max":279.41,"Temp_min":279.41,"Data":"2022-01-24 21:00:00"}},{"Main":{"Speed":1.81,"Feels_Like":277.66,"Temp":278.96,"Temp_max":278.96,"Temp_min":278.96,"Data":"2022-01-25 00:00:00"}},{"Main":{"Speed":2.16,"Feels_Like":276.89,"Temp":278.6,"Temp_max":278.6,"Temp_min":278.6,"Data":"2022-01-25 03:00:00"}},{"Main":{"Speed":2.38,"Feels_Like":276.46,"Temp":278.41,"Temp_max":278.41,"Temp_min":278.41,"Data":"2022-01-25 06:00:00"}},{"Main":{"Speed":1.3,"Feels_Like":278.75,"Temp":278.75,"Temp_max":278.75,"Temp_min":278.75,"Data":"2022-01-25 09:00:00"}},{"Main":{"Speed":1.63,"Feels_Like":279.23,"Temp":280.15,"Temp_max":280.15,"Temp_min":280.15,"Data":"2022-01-25 12:00:00"}},{"Main":{"Speed":2.18,"Feels_Like":279.31,"Temp":280.68,"Temp_max":280.68,"Temp_min":280.68,"Data":"2022-01-25 15:00:00"}},{"Main":{"Speed":2.59,"Feels_Like":277.1,"Temp":279.1,"Temp_max":279.1,"Temp_min":279.1,"Data":"2022-01-25 18:00:00"}}],"Name":"Venice"}
{"Id":3164603,"JSON-DATI ":[{"Main":{"Speed":2.07,"Feels_Like":273.73,"Temp":275.82,"Temp_max":278.64,"Temp_min":275.82,"Data":"2022-01-20 21:00:00"}},{"Main":{"Speed":1.8,"Feels_Like":274.85,"Temp":276.52,"Temp_max":277.93,"Temp_min":276.52,"Data":"2022-01-21 00:00:00"}},{"Main":{"Speed":2.85,"Feels_Like":274.18,"Temp":276.82,"Temp_max":277.32,"Temp_min":276.82,"Data":"2022-01-21 03:00:00"}},{"Main":{"Speed":5.19,"Feels_Like":272.8,"Temp":276.88,"Temp_max":276.88,"Temp_min":276.88,"Data":"2022-01-21 06:00:00"}},{"Main":{"Speed":6.25,"Feels_Like":274.31,"Temp":278.44,"Temp_max":278.44,"Temp_min":278.44,"Data":"2022-01-21 09:00:00"}},{"Main":{"Speed":5.86,"Feels_Like":276.87,"Temp":280.33,"Temp_max":280.33,"Temp_min":280.33,"Data":"2022-01-21 12:00:00"}},{"Main":{"Speed":2.97,"Feels_Like":277.85,"Temp":279.96,"Temp_max":279.96,"Temp_min":279.96,"Data":"2022-01-21 15:00:00"}},{"Main":{"Speed":2.61,"Feels_Like":276.22,"Temp":278.37,"Temp_max":278.37,"Temp_min":278.37,"Data":"2022-01-21 18:00:00"}},{"Main":{"Speed":2.15,"Feels_Like":275.33,"Temp":277.26,"Temp_max":277.26,"Temp_min":277.26,"Data":"2022-01-21 21:00:00"}},{"Main":{"Speed":1.67,"Feels_Like":275.13,"Temp":276.62,"Temp_max":276.62,"Temp_min":276.62,"Data":"2022-01-22 00:00:00"}},{"Main":{"Speed":2.05,"Feels_Like":273.64,"Temp":275.73,"Temp_max":275.73,"Temp_min":275.73,"Data":"2022-01-22 03:00:00"}},{"Main":{"Speed":1.37,"Feels_Like":274.01,"Temp":275.27,"Temp_max":275.27,"Temp_min":275.27,"Data":"2022-01-22 06:00:00"}},{"Main":{"Speed":3.11,"Feels_Like":274.07,"Temp":276.9,"Temp_max":276.9,"Temp_min":276.9,"Data":"2022-01-22 09:00:00"}},{"Main":{"Speed":3.24,"Feels_Like":276.52,"Temp":279.01,"Temp_max":279.01,"Temp_min":279.01,"Data":"2022-01-22 12:00:00"}},{"Main":{"Speed":1.12,"Feels_Like":279.08,"Temp":279.08,"Temp_max":279.08,"Temp_min":279.08,"Data":"2022-01-22 15:00:00"}},{"Main":{"Speed":1.76,"Feels_Like":275.91,"Temp":277.4,"Temp_max":277.4,"Temp_min":277.4,"Data":"2022-01-22 18:00:00"}},{"Main":{"Speed":2.1,"Feels_Like":274.8,"Temp":276.77,"Temp_max":276.77,"Temp_min":276.77,"Data":"2022-01-22 21:00:00"}},{"Main":{"Speed":2.36,"Feels_Like":273.85,"Temp":276.18,"Temp_max":276.18,"Temp_min":276.18,"Data":"2022-01-23 00:00:00"}},{"Main":{"Speed":1.98,"Feels_Like":273.86,"Temp":275.85,"Temp_max":275.85,"Temp_min":275.85,"Data":"2022-01-23 03:00:00"}},{"Main":{"Speed":1.99,"Feels_Like":273.86,"Temp":275.86,"Temp_max":275.86,"Temp_min":275.86,"Data":"2022-01-23 06:00:00"}},{"Main":{"Speed":1.67,"Feels_Like":275.75,"Temp":277.16,"Temp_max":277.16,"Temp_min":277.16,"Data":"2022-01-23 09:00:00"}},{"Main":{"Speed":0.67,"Feels_Like":279.29,"Temp":279.29,"Temp_max":279.29,"Temp_min":279.29,"Data":"2022-01-23 12:00:00"}},{"Main":{"Speed":0.63,"Feels_Like":279.54,"Temp":279.54,"Temp_max":279.54,"Temp_min":279.54,"Data":"2022-01-23 15:00:00"}},{"Main":{"Speed":1.51,"Feels_Like":277.05,"Temp":278.12,"Temp_max":278.12,"Temp_min":278.12,"Data":"2022-01-23 18:00:00"}},{"Main":{"Speed":1.83,"Feels_Like":275.97,"Temp":277.52,"Temp_max":277.52,"Temp_min":277.52,"Data":"2022-01-23 21:00:00"}},{"Main":{"Speed":1.35,"Feels_Like":276.22,"Temp":277.19,"Temp_max":277.19,"Temp_min":277.19,"Data":"2022-01-24 00:00:00"}},{"Main":{"Speed":1.55,"Feels_Like":275.61,"Temp":276.91,"Temp_max":276.91,"Temp_min":276.91,"Data":"2022-01-24 03:00:00"}},{"Main":{"Speed":2.45,"Feels_Like":274.01,"Temp":276.39,"Temp_max":276.39,"Temp_min":276.39,"Data":"2022-01-24 06:00:00"}},{"Main":{"Speed":2.38,"Feels_Like":275.8,"Temp":277.85,"Temp_max":277.85,"Temp_min":277.85,"Data":"2022-01-24 09:00:00"}},{"Main":{"Speed":1.47,"Feels_Like":279.39,"Temp":280.13,"Temp_max":280.13,"Temp_min":280.13,"Data":"2022-01-24 12:00:00"}},{"Main":{"Speed":0.54,"Feels_Like":280.38,"Temp":280.38,"Temp_max":280.38,"Temp_min":280.38,"Data":"2022-01-24 15:00:00"}},{"Main":{"Speed":0.23,"Feels_Like":279.86,"Temp":279.86,"Temp_max":279.86,"Temp_min":279.86,"Data":"2022-01-24 18:00:00"}},{"Main":{"Speed":1.18,"Feels_Like":279.41,"Temp":279.41,"Temp_max":279.41,"Temp_min":279.41,"Data":"2022-01-24 21:00:00"}},{"Main":{"Speed":1.81,"Feels_Like":277.66,"Temp":278.96,"Temp_max":278.96,"Temp_min":278.96,"Data":"2022-01-25 00:00:00"}},{"Main":{"Speed":2.16,"Feels_Like":276.89,"Temp":278.6,"Temp_max":278.6,"Temp_min":278.6,"Data":"2022-01-25 03:00:00"}},{"Main":{"Speed":2.38,"Feels_Like":276.46,"Temp":278.41,"Temp_max":278.41,"Temp_min":278.41,"Data":"2022-01-25 06:00:00"}},{"Main":{"Speed":1.3,"Feels_Like":278.75,"Temp":278.75,"Temp_max":278.75,"Temp_min":278.75,"Data":"2022-01-25 09:00:00"}},{"Main":{"Speed":1.63,"Feels_Like":279.23,"Temp":280.15,"Temp_max":280.15,"Temp_min":280.15,"Data":"2022-01-25 12:00:00"}},{"Main":{"Speed":2.18,"Feels_Like":279.31,"Temp":280.68,"Temp_max":280.68,"Temp_min":280.68,"Data":"2022-01-25 15:00:00"}},{"Main":{"Speed":2.59,"Feels_Like":277.1,"Temp":279.1,"Temp_max":279.1,"Temp_min":279.1,"Data":"2022-01-25 18:00:00"}}],"Name":"Venice"}
{"Id":3164603,"JSON-DATI ":[{"Main":{"Speed":2.07,"Feels_Like":273.73,"Temp":275.82,"Temp_max":278.64,"Temp_min":275.82,"Data":"2022-01-20 21:00:00"}},{"Main":{"Speed":1.8,"Feels_Like":274.85,"Temp":276.52,"Temp_max":277.93,"Temp_min":276.52,"Data":"2022-01-21 00:00:00"}},{"Main":{"Speed":2.85,"Feels_Like":274.18,"Temp":276.82,"Temp_max":277.32,"Temp_min":276.82,"Data":"2022-01-21 03:00:00"}},{"Main":{"Speed":5.19,"Feels_Like":272.8,"Temp":276.88,"Temp_max":276.88,"Temp_min":276.88,"Data":"2022-01-21 06:00:00"}},{"Main":{"Speed":6.25,"Feels_Like":274.31,"Temp":278.44,"Temp_max":278.44,"Temp_min":278.44,"Data":"2022-01-21 09:00:00"}},{"Main":{"Speed":5.86,"Feels_Like":276.87,"Temp":280.33,"Temp_max":280.33,"Temp_min":280.33,"Data":"2022-01-21 12:00:00"}},{"Main":{"Speed":2.97,"Feels_Like":277.85,"Temp":279.96,"Temp_max":279.96,"Temp_min":279.96,"Data":"2022-01-21 15:00:00"}},{"Main":{"Speed":2.61,"Feels_Like":276.22,"Temp":278.37,"Temp_max":278.37,"Temp_min":278.37,"Data":"2022-01-21 18:00:00"}},{"Main":{"Speed":2.15,"Feels_Like":275.33,"Temp":277.26,"Temp_max":277.26,"Temp_min":277.26,"Data":"2022-01-21 21:00:00"}},{"Main":{"Speed":1.67,"Feels_Like":275.13,"Temp":276.62,"Temp_max":276.62,"Temp_min":276.62,"Data":"2022-01-22 00:00:00"}},{"Main":{"Speed":2.05,"Feels_Like":273.64,"Temp":275.73,"Temp_max":275.73,"Temp_min":275.73,"Data":"2022-01-22 03:00:00"}},{"Main":{"Speed":1.37,"Feels_Like":274.01,"Temp":275.27,"Temp_max":275.27,"Temp_min":275.27,"Data":"2022-01-22 06:00:00"}},{"Main":{"Speed":3.11,"Feels_Like":274.07,"Temp":276.9,"Temp_max":276.9,"Temp_min":276.9,"Data":"2022-01-22 09:00:00"}},{"Main":{"Speed":3.24,"Feels_Like":276.52,"Temp":279.01,"Temp_max":279.01,"Temp_min":279.01,"Data":"2022-01-22 12:00:00"}},{"Main":{"Speed":1.12,"Feels_Like":279.08,"Temp":279.08,"Temp_max":279.08,"Temp_min":279.08,"Data":"2022-01-22 15:00:00"}},{"Main":{"Speed":1.76,"Feels_Like":275.91,"Temp":277.4,"Temp_max":277.4,"Temp_min":277.4,"Data":"2022-01-22 18:00:00"}},{"Main":{"Speed":2.1,"Feels_Like":274.8,"Temp":276.77,"Temp_max":276.77,"Temp_min":276.77,"Data":"2022-01-22 21:00:00"}},{"Main":{"Speed":2.36,"Feels_Like":273.85,"Temp":276.18,"Temp_max":276.18,"Temp_min":276.18,"Data":"2022-01-23 00:00:00"}},{"Main":{"Speed":1.98,"Feels_Like":273.86,"Temp":275.85,"Temp_max":275.85,"Temp_min":275.85,"Data":"2022-01-23 03:00:00"}},{"Main":{"Speed":1.99,"Feels_Like":273.86,"Temp":275.86,"Temp_max":275.86,"Temp_min":275.86,"Data":"2022-01-23 06:00:00"}},{"Main":{"Speed":1.67,"Feels_Like":275.75,"Temp":277.16,"Temp_max":277.16,"Temp_min":277.16,"Data":"2022-01-23 09:00:00"}},{"Main":{"Speed":0.67,"Feels_Like":279.29,"Temp":279.29,"Temp_max":279.29,"Temp_min":279.29,"Data":"2022-01-23 12:00:00"}},{"Main":{"Speed":0.63,"Feels_Like":279.54,"Temp":279.54,"Temp_max":279.54,"Temp_min":279.54,"Data":"2022-01-23 15:00:00"}},{"Main":{"Speed":1.51,"Feels_Like":277.05,"Temp":278.12,"Temp_max":278.12,"Temp_min":278.12,"Data":"2022-01-23 18:00:00"}},{"Main":{"Speed":1.83,"Feels_Like":275.97,"Temp":277.52,"Temp_max":277.52,"Temp_min":277.52,"Data":"2022-01-23 21:00:00"}},{"Main":{"Speed":1.35,"Feels_Like":276.22,"Temp":277.19,"Temp_max":277.19,"Temp_min":277.19,"Data":"2022-01-24 00:00:00"}},{"Main":{"Speed":1.55,"Feels_Like":275.61,"Temp":276.91,"Temp_max":276.91,"Temp_min":276.91,"Data":"2022-01-24 03:00:00"}},{"Main":{"Speed":2.45,"Feels_Like":274.01,"Temp":276.39,"Temp_max":276.39,"Temp_min":276.39,"Data":"2022-01-24 06:00:00"}},{"Main":{"Speed":2.38,"Feels_Like":275.8,"Temp":277.85,"Temp_max":277.85,"Temp_min":277.85,"Data":"2022-01-24 09:00:00"}},{"Main":{"Speed":1.47,"Feels_Like":279.39,"Temp":280.13,"Temp_max":280.13,"Temp_min":280.13,"Data":"2022-01-24 12:00:00"}},{"Main":{"Speed":0.54,"Feels_Like":280.38,"Temp":280.38,"Temp_max":280.38,"Temp_min":280.38,"Data":"2022-01-24 15:00:00"}},{"Main":{"Speed":0.23,"Feels_Like":279.86,"Temp":279.86,"Temp_max":279.86,"Temp_min":279.86,"Data":"2022-01-24 18:00:00"}},{"Main":{"Speed":1.18,"Feels_Like":279.41,"Temp":279.41,"Temp_max":279.41,"Temp_min":279.41,"Data":"2022-01-24 21:00:00"}},{"Main":{"Speed":1.81,"Feels_Like":277.66,"Temp":278.96,"Temp_max":278.96,"Temp_min":278.96,"Data":"2022-01-25 00:00:00"}},{"Main":{"Speed":2.16,"Feels_Like":276.89,"Temp":278.6,"Temp_max":278.6,"Temp_min":278.6,"Data":"2022-01-25 03:00:00"}},{"Main":{"Speed":2.38,"Feels_Like":276.46,"Temp":278.41,"Temp_max":278.41,"Temp_min":278.41,"Data":"2022-01-25 06:00:00"}},{"Main":{"Speed":1.3,"Feels_Like":278.75,"Temp":278.75,"Temp_max":278.75,"Temp_min":278.75,"Data":"2022-01-25 09:00:00"}},{"Main":{"Speed":1.63,"Feels_Like":279.23,"Temp":280.15,"Temp_max":280.15,"Temp_min":280.15,"Data":"2022-01-25 12:00:00"}},{"Main":{"Speed":2.18,"Feels_Like":279.31,"Temp":280.68,"Temp_max":280.68,"Temp_min":280.68,"Data":"2022-01-25 15:00:00"}},{"Main":{"Speed":2.59,"Feels_Like":277.1,"Temp":279.1,"Temp_max":279.1,"Temp_min":279.1,"Data":"2022-01-25 18:00:00"}}],"Name":"Venice"}
{"Id":3164603,"JSON-DATI ":[{"Main":{"Speed":2.07,"Feels_Like":273.73,"Temp":275.82,"Temp_max":278.64,"Temp_min":275.82,"Data":"2022-01-20 21:00:00"}},{"Main":{"Speed":1.8,"Feels_Like":274.85,"Temp":276.52,"Temp_max":277.93,"Temp_min":276.52,"Data":"2022-01-21 00:00:00"}},{"Main":{"Speed":2.85,"Feels_Like":274.18,"Temp":276.82,"Temp_max":277.32,"Temp_min":276.82,"Data":"2022-01-21 03:00:00"}},{"Main":{"Speed":5.19,"Feels_Like":272.8,"Temp":276.88,"Temp_max":276.88,"Temp_min":276.88,"Data":"2022-01-21 06:00:00"}},{"Main":{"Speed":6.25,"Feels_Like":274.31,"Temp":278.44,"Temp_max":278.44,"Temp_min":278.44,"Data":"2022-01-21 09:00:00"}},{"Main":{"Speed":5.86,"Feels_Like":276.87,"Temp":280.33,"Temp_max":280.33,"Temp_min":280.33,"Data":"2022-01-21 12:00:00"}},{"Main":{"Speed":2.97,"Feels_Like":277.85,"Temp":279.96,"Temp_max":279.96,"Temp_min":279.96,"Data":"2022-01-21 15:00:00"}},{"Main":{"Speed":2.61,"Feels_Like":276.22,"Temp":278.37,"Temp_max":278.37,"Temp_min":278.37,"Data":"2022-01-21 18:00:00"}},{"Main":{"Speed":2.15,"Feels_Like":275.33,"Temp":277.26,"Temp_max":277.26,"Temp_min":277.26,"Data":"2022-01-21 21:00:00"}},{"Main":{"Speed":1.67,"Feels_Like":275.13,"Temp":276.62,"Temp_max":276.62,"Temp_min":276.62,"Data":"2022-01-22 00:00:00"}},{"Main":{"Speed":2.05,"Feels_Like":273.64,"Temp":275.73,"Temp_max":275.73,"Temp_min":275.73,"Data":"2022-01-22 03:00:00"}},{"Main":{"Speed":1.37,"Feels_Like":274.01,"Temp":275.27,"Temp_max":275.27,"Temp_min":275.27,"Data":"2022-01-22 06:00:00"}},{"Main":{"Speed":3.11,"Feels_Like":274.07,"Temp":276.9,"Temp_max":276.9,"Temp_min":276.9,"Data":"2022-01-22 09:00:00"}},{"Main":{"Speed":3.24,"Feels_Like":276.52,"Temp":279.01,"Temp_max":279.01,"Temp_min":279.01,"Data":"2022-01-22 12:00:00"}},{"Main":{"Speed":1.12,"Feels_Like":279.08,"Temp":279.08,"Temp_max":279.08,"Temp_min":279.08,"Data":"2022-01-22 15:00:00"}},{"Main":{"Speed":1.76,"Feels_Like":275.91,"Temp":277.4,"Temp_max":277.4,"Temp_min":277.4,"Data":"2022-01-22 18:00:00"}},{"Main":{"Speed":2.1,"Feels_Like":274.8,"Temp":276.77,"Temp_max":276.77,"Temp_min":276.77,"Data":"2022-01-22 21:00:00"}},{"Main":{"Speed":2.36,"Feels_Like":273.85,"Temp":276.18,"Temp_max":276.18,"Temp_min":276.18,"Data":"2022-01-23 00:00:00"}},{"Main":{"Speed":1.98,"Feels_Like":273.86,"Temp":275.85,"Temp_max":275.85,"Temp_min":275.85,"Data":"2022-01-23 03:00:00"}},{"Main":{"Speed":1.99,"Feels_Like":273.86,"Temp":275.86,"Temp_max":275.86,"Temp_min":275.86,"Data":"2022-01-23 06:00:00"}},{"Main":{"Speed":1.67,"Feels_Like":275.75,"Temp":277.16,"Temp_max":277.16,"Temp_min":277.16,"Data":"2022-01-23 09:00:00"}},{"Main":{"Speed":0.67,"Feels_Like":279.29,"Temp":279.29,"Temp_max":279.29,"Temp_min":279.29,"Data":"2022-01-23 12:00:00"}},{"Main":{"Speed":0.63,"Feels_Like":279.54,"Temp":279.54,"Temp_max":279.54,"Temp_min":279.54,"Data":"2022-01-23 15:00:00"}},{"Main":{"Speed":1.51,"Feels_Like":277.05,"Temp":278.12,"Temp_max":278.12,"Temp_min":278.12,"Data":"2022-01-23 18:00:00"}},{"Main":{"Speed":1.83,"Feels_Like":275.97,"Temp":277.52,"Temp_max":277.52,"Temp_min":277.52,"Data":"2022-01-23 21:00:00"}},{"Main":{"Speed":1.35,"Feels_Like":276.22,"Temp":277.19,"Temp_max":277.19,"Temp_min":277.19,"Data":"2022-01-24 00:00:00"}},{"Main":{"Speed":1.55,"Feels_Like":275.61,"Temp":276.91,"Temp_max":276.91,"Temp_min":276.91,"Data":"2022-01-24 03:00:00"}},{"Main":{"Speed":2.45,"Feels_Like":274.01,"Temp":276.39,"Temp_max":276.39,"Temp_min":276.39,"Data":"2022-01-24 06:00:00"}},{"Main":{"Speed":2.38,"Feels_Like":275.8,"Temp":277.85,"Temp_max":277.85,"Temp_min":277.85,"Data":"2022-01-24 09:00:00"}},{"Main":{"Speed":1.47,"Feels_Like":279.39,"Temp":280.13,"Temp_max":280.13,"Temp_min":280.13,"Data":"2022-01-24 12:00:00"}},{"Main":{"Speed":0.54,"Feels_Like":280.38,"Temp":280.38,"Temp_max":280.38,"Temp_min":280.38,"Data":"2022-01-24 15:00:00"}},{"Main":{"Speed":0.23,"Feels_Like":279.86,"Temp":279.86,"Temp_max":279.86,"Temp_min":279.86,"Data":"2022-01-24 18:00:00"}},{"Main":{"Speed":1.18,"Feels_Like":279.41,"Temp":279.41,"Temp_max":279.41,"Temp_min":279.41,"Data":"2022-01-24 21:00:00"}},{"Main":{"Speed":1.81,"Feels_Like":277.66,"Temp":278.96,"Temp_max":278.96,"Temp_min":278.96,"Data":"2022-01-25 00:00:00"}},{"Main":{"Speed":2.16,"Feels_Like":276.89,"Temp":278.6,"Temp_max":278.6,"Temp_min":278.6,"Data":"2022-01-25 03:00:00"}},{"Main":{"Speed":2.38,"Feels_Like":276.46,"Temp":278.41,"Temp_max":278.41,"Temp_min":278.41,"Data":"2022-01-25 06:00:00"}},{"Main":{"Speed":1.3,"Feels_Like":278.75,"Temp":278.75,"Temp_max":278.75,"Temp_min":278.75,"Data":"2022-01-25 09:00:00"}},{"Main":{"Speed":1.63,"Feels_Like":279.23,"Temp":280.15,"Temp_max":280.15,"Temp_min":280.15,"Data":"2022-01-25 12:00:00"}},{"Main":{"Speed":2.18,"Feels_Like":279.31,"Temp":280.68,"Temp_max":280.68,"Temp_min":280.68,"Data":"2022-01-25 15:00:00"}},{"Main":{"Speed":2.59,"Feels_Like":277.1,"Temp":279.1,"Temp_max":279.1,"Temp_min":279.1,"Data":"2022-01-25 18:00:00"}}],"Name":"Venice"}
{"Id":3164603,"JSON-DATI ":[{"Main":{"Speed":2.07,"Feels_Like":273.73,"Temp":275.82,"Temp_max":278.64,"Temp_min":275.82,"Data":"2022-01-20 21:00:00"}},{"Main":{"Speed":1.8,"Feels_Like":274.85,"Temp":276.52,"Temp_max":277.93,"Temp_min":276.52,"Data":"2022-01-21 00:00:00"}},{"Main":{"Speed":2.85,"Feels_Like":274.18,"Temp":276.82,"Temp_max":277.32,"Temp_min":276.82,"Data":"2022-01-21 03:00:00"}},{"Main":{"Speed":5.19,"Feels_Like":272.8,"Temp":276.88,"Temp_max":276.88,"Temp_min":276.88,"Data":"2022-01-21 06:00:00"}},{"Main":{"Speed":6.25,"Feels_Like":274.31,"Temp":278.44,"Temp_max":278.44,"Temp_min":278.44,"Data":"2022-01-21 09:00:00"}},{"Main":{"Speed":5.86,"Feels_Like":276.87,"Temp":280.33,"Temp_max":280.33,"Temp_min":280.33,"Data":"2022-01-21 12:00:00"}},{"Main":{"Speed":2.97,"Feels_Like":277.85,"Temp":279.96,"Temp_max":279.96,"Temp_min":279.96,"Data":"2022-01-21 15:00:00"}},{"Main":{"Speed":2.61,"Feels_Like":276.22,"Temp":278.37,"Temp_max":278.37,"Temp_min":278.37,"Data":"2022-01-21 18:00:00"}},{"Main":{"Speed":2.15,"Feels_Like":275.33,"Temp":277.26,"Temp_max":277.26,"Temp_min":277.26,"Data":"2022-01-21 21:00:00"}},{"Main":{"Speed":1.67,"Feels_Like":275.13,"Temp":276.62,"Temp_max":276.62,"Temp_min":276.62,"Data":"2022-01-22 00:00:00"}},{"Main":{"Speed":2.05,"Feels_Like":273.64,"Temp":275.73,"Temp_max":275.73,"Temp_min":275.73,"Data":"2022-01-22 03:00:00"}},{"Main":{"Speed":1.37,"Feels_Like":274.01,"Temp":275.27,"Temp_max":275.27,"Temp_min":275.27,"Data":"2022-01-22 06:00:00"}},{"Main":{"Speed":3.11,"Feels_Like":274.07,"Temp":276.9,"Temp_max":276.9,"Temp_min":276.9,"Data":"2022-01-22 09:00:00"}},{"Main":{"Speed":3.24,"Feels_Like":276.52,"Temp":279.01,"Temp_max":279.01,"Temp_min":279.01,"Data":"2022-01-22 12:00:00"}},{"Main":{"Speed":1.12,"Feels_Like":279.08,"Temp":279.08,"Temp_max":279.08,"Temp_min":279.08,"Data":"2022-01-22 15:00:00"}},{"Main":{"Speed":1.76,"Feels_Like":275.91,"Temp":277.4,"Temp_max":277.4,"Temp_min":277.4,"Data":"2022-01-22 18:00:00"}},{"Main":{"Speed":2.1,"Feels_Like":274.8,"Temp":276.77,"Temp_max":276.77,"Temp_min":276.77,"Data":"2022-01-22 21:00:00"}},{"Main":{"Speed":2.36,"Feels_Like":273.85,"Temp":276.18,"Temp_max":276.18,"Temp_min":276.18,"Data":"2022-01-23 00:00:00"}},{"Main":{"Speed":1.98,"Feels_Like":273.86,"Temp":275.85,"Temp_max":275.85,"Temp_min":275.85,"Data":"2022-01-23 03:00:00"}},{"Main":{"Speed":1.99,"Feels_Like":273.86,"Temp":275.86,"Temp_max":275.86,"Temp_min":275.86,"Data":"2022-01-23 06:00:00"}},{"Main":{"Speed":1.67,"Feels_Like":275.75,"Temp":277.16,"Temp_max":277.16,"Temp_min":277.16,"Data":"2022-01-23 09:00:00"}},{"Main":{"Speed":0.67,"Feels_Like":279.29,"Temp":279.29,"Temp_max":279.29,"Temp_min":279.29,"Data":"2022-01-23 12:00:00"}},{"Main":{"Speed":0.63,"Feels_Like":279.54,"Temp":279.54,"Temp_max":279.54,"Temp_min":279.54,"Data":"2022-01-23 15:00:00"}},{"Main":{"Speed":1.51,"Feels_Like":277.05,"Temp":278.12,"Temp_max":278.12,"Temp_min":278.12,"Data":"2022-01-23 18:00:00"}},{"Main":{"Speed":1.83,"Feels_Like":275.97,"Temp":277.52,"Temp_max":277.52,"Temp_min":277.52,"Data":"2022-01-23 21:00:00"}},{"Main":{"Speed":1.35,"Feels_Like":276.22,"Temp":277.19,"Temp_max":277.19,"Temp_min":277.19,"Data":"2022-01-24 00:00:00"}},{"Main":{"Speed":1.55,"Feels_Like":275.61,"Temp":276.91,"Temp_max":276.91,"Temp_min":276.91,"Data":"2022-01-24 03:00:00"}},{"Main":{"Speed":2.45,"Feels_Like":274.01,"Temp":276.39,"Temp_max":276.39,"Temp_min":276.39,"Data":"2022-01-24 06:00:00"}},{"Main":{"Speed":2.38,"Feels_Like":275.8,"Temp":277.85,"Temp_max":277.85,"Temp_min":277.85,"Data":"2022-01-24 09:00:00"}},{"Main":{"Speed":1.47,"Feels_Like":279.39,"Temp":280.13,"Temp_max":280.13,"Temp_min":280.13,"Data":"2022-01-24 12:00:00"}},{"Main":{"Speed":0.54,"Feels_Like":280.38,"Temp":280.38,"Temp_max":280.38,"Temp_min":280.38,"Data":"2022-01-24 15:00:00"}},{"Main":{"Speed":0.23,"Feels_Like":279.86,"Temp":279.86,"Temp_max":279.86,"Temp_min":279.86,"Data":"2022-01-24 18:00:00"}},{"Main":{"Speed":1.18,"Feels_Like":279.41,"Temp":279.41,"Temp_max":279.41,"Temp_min":279.41,"Data":"2022-01-24 21:00:00"}},{"Main":{"Speed":1.81,"Feels_Like":277.66,"Temp":278.96,"Temp_max":278.96,"Temp_min":278.96,"Data":"2022-01-25 00:00:00"}},{"Main":{"Speed":2.16,"Feels_Like":276.89,"Temp":278.6,"Temp_max":278.6,"Temp_min":278.6,"Data":"2022-01-25 03:00:00"}},{"Main":{"Speed":2.38,"Feels_Like":276.46,"Temp":278.41,"Temp_max":278.41,"Temp_min":278.41,"Data":"2022-01-25 06:00:00"}},{"Main":{"Speed":1.3,"Feels_Like":278.75,"Temp":278.75,"Temp_max":278.75,"Temp_min":278.75,"Data":"2022-01-25 09:00:00"}},{"Main":{"Speed":1.63,"Feels_Like":279.23,"Temp":280.15,"Temp_max":280.15,"Temp_min":280.15,"Data":"2022-01-25 12:00:00"}},{"Main":{"Speed":2.18,"Feels_Like":279.31,"Temp":280.68,"Temp_max":280.68,"Temp_min":280.68,"Data":"2022-01-25 15:00:00"}},{"Main":{"Speed":2.59,"Feels_Like":277.1,"Temp":279.1,"Temp_max":279.1,"Temp_min":279.1,"Data":"2022-01-25 18:00:00"}}],"Name":"Venice"}
{"Id":3164603,"JSON-DATI ":[{"Main":{"Speed":2.07,"Feels_Like":273.73,"Temp":275.82,"Temp_max":278.64,"Temp_min":275.82,"Data":"2022-01-20 21:00:00"}},{"Main":{"Speed":1.8,"Feels_Like":274.85,"Temp":276.52,"Temp_max":277.93,"Temp_min":276.52,"Data":"2022-01-21 00:00:00"}},{"Main":{"Speed":2.85,"Feels_Like":274.18,"Temp":276.82,"Temp_max":277.32,"Temp_min":276.82,"Data":"2022-01-21 03:00:00"}},{"Main":{"Speed":5.19,"Feels_Like":272.8,"Temp":276.88,"Temp_max":276.88,"Temp_min":276.88,"Data":"2022-01-21 06:00:00"}},{"Main":{"Speed":6.25,"Feels_Like":274.31,"Temp":278.44,"Temp_max":278.44,"Temp_min":278.44,"Data":"2022-01-21 09:00:00"}},{"Main":{"Speed":5.86,"Feels_Like":276.87,"Temp":280.33,"Temp_max":280.33,"Temp_min":280.33,"Data":"2022-01-21 12:00:00"}},{"Main":{"Speed":2.97,"Feels_Like":277.85,"Temp":279.96,"Temp_max":279.96,"Temp_min":279.96,"Data":"2022-01-21 15:00:00"}},{"Main":{"Speed":2.61,"Feels_Like":276.22,"Temp":278.37,"Temp_max":278.37,"Temp_min":278.37,"Data":"2022-01-21 18:00:00"}},{"Main":{"Speed":2.15,"Feels_Like":275.33,"Temp":277.26,"Temp_max":277.26,"Temp_min":277.26,"Data":"2022-01-21 21:00:00"}},{"Main":{"Speed":1.67,"Feels_Like":275.13,"Temp":276.62,"Temp_max":276.62,"Temp_min":276.62,"Data":"2022-01-22 00:00:00"}},{"Main":{"Speed":2.05,"Feels_Like":273.64,"Temp":275.73,"Temp_max":275.73,"Temp_min":275.73,"Data":"2022-01-22 03:00:00"}},{"Main":{"Speed":1.37,"Feels_Like":274.01,"Temp":275.27,"Temp_max":275.27,"Temp_min":275.27,"Data":"2022-01-22 06:00:00"}},{"Main":{"Speed":3.11,"Feels_Like":274.07,"Temp":276.9,"Temp_max":276.9,"Temp_min":276.9,"Data":"2022-01-22 09:00:00"}},{"Main":{"Speed":3.24,"Feels_Like":276.52,"Temp":279.01,"Temp_max":279.01,"Temp_min":279.01,"Data":"2022-01-22 12:00:00"}},{"Main":{"Speed":1.12,"Feels_Like":279.08,"Temp":279.08,"Temp_max":279.08,"Temp_min":279.08,"Data":"2022-01-22 15:00:00"}},{"Main":{"Speed":1.76,"Feels_Like":275.91,"Temp":277.4,"Temp_max":277.4,"Temp_min":277.4,"Data":"2022-01-22 18:00:00"}},{"Main":{"Speed":2.1,"Feels_Like":274.8,"Temp":276.77,"Temp_max":276.77,"Temp_min":276.77,"Data":"2022-01-22 21:00:00"}},{"Main":{"Speed":2.36,"Feels_Like":273.85,"Temp":276.18,"Temp_max":276.18,"Temp_min":276.18,"Data":"2022-01-23 00:00:00"}},{"Main":{"Speed":1.98,"Feels_Like":273.86,"Temp":275.85,"Temp_max":275.85,"Temp_min":275.85,"Data":"2022-01-23 03:00:00"}},{"Main":{"Speed":1.99,"Feels_Like":273.86,"Temp":275.86,"Temp_max":275.86,"Temp_min":275.86,"Data":"2022-01-23 06:00:00"}},{"Main":{"Speed":1.67,"Feels_Like":275.75,"Temp":277.16,"Temp_max":277.16,"Temp_min":277.16,"Data":"2022-01-23 09:00:00"}},{"Main":{"Speed":0.67,"Feels_Like":279.29,"Temp":279.29,"Temp_max":279.29,"Temp_min":279.29,"Data":"2022-01-23 12:00:00"}},{"Main":{"Speed":0.63,"Feels_Like":279.54,"Temp":279.54,"Temp_max":279.54,"Temp_min":279.54,"Data":"2022-01-23 15:00:00"}},{"Main":{"Speed":1.51,"Feels_Like":277.05,"Temp":278.12,"Temp_max":278.12,"Temp_min":278.12,"Data":"2022-01-23 18:00:00"}},{"Main":{"Speed":1.83,"Feels_Like":275.97,"Temp":277.52,"Temp_max":277.52,"Temp_min":277.52,"Data":"2022-01-23 21:00:00"}},{"Main":{"Speed":1.35,"Feels_Like":276.22,"Temp":277.19,"Temp_max":277.19,"Temp_min":277.19,"Data":"2022-01-24 00:00:00"}},{"Main":{"Speed":1.55,"Feels_Like":275.61,"Temp":276.91,"Temp_max":276.91,"Temp_min":276.91,"Data":"2022-01-24 03:00:00"}},{"Main":{"Speed":2.45,"Feels_Like":274.01,"Temp":276.39,"Temp_max":276.39,"Temp_min":276.39,"Data":"2022-01-24 06:00:00"}},{"Main":{"Speed":2.38,"Feels_Like":275.8,"Temp":277.85,"Temp_max":277.85,"Temp_min":277.85,"Data":"2022-01-24 09:00:00"}},{"Main":{"Speed":1.47,"Feels_Like":279.39,"Temp":280.13,"Temp_max":280.13,"Temp_min":280.13,"Data":"2022-01-24 12:00:00"}},{"Main":{"Speed":0.54,"Feels_Like":280.38,"Temp":280.38,"Temp_max":280.38,"Temp_min":280.38,"Data":"2022-01-24 15:00:00"}},{"Main":{"Speed":0.23,"Feels_Like":279.86,"Temp":279.86,"Temp_max":279.86,"Temp_min":279.86,"Data":"2022-01-24 18:00:00"}},{"Main":{"Speed":1.18,"Feels_Like":279.41,"Temp":279.41,"Temp_max":279.41,"Temp_min":279.41,"Data":"2022-01-24 21:00:00"}},{"Main":{"Speed":1.81,"Feels_Like":277.66,"Temp":278.96,"Temp_max":278.96,"Temp_min":278.96,"Data":"2022-01-25 00:00:00"}},{"Main":{"Speed":2.16,"Feels_Like":276.89,"Temp":278.6,"Temp_max":278.6,"Temp_min":278.6,"Data":"2022-01-25 03:00:00"}},{"Main":{"Speed":2.38,"Feels_Like":276.46,"Temp":278.41,"Temp_max":278.41,"Temp_min":278.41,"Data":"2022-01-25 06:00:00"}},{"Main":{"Speed":1.3,"Feels_Like":278.75,"Temp":278.75,"Temp_max":278.75,"Temp_min":278.75,"Data":"2022-01-25 09:00:00"}},{"Main":{"Speed":1.63,"Feels_Like":279.23,"Temp":280.15,"Temp_max":280.15,"Temp_min":280.15,"Data":"2022-01-25 12:00:00"}},{"Main":{"Speed":2.18,"Feels_Like":279.31,"Temp":280.68,"Temp_max":280.68,"Temp_min":280.68,"Data":"2022-01-25 15:00:00"}},{"Main":{"Speed":2.59,"Feels_Like":277.1,"Temp":279.1,"Temp_max":279.1,"Temp_min":279.1,"Data":"2022-01-25 18:00:00"}}],"Name":"Venice"}
{"Id":3164603,"JSON-DATI ":[{"Main":{"Speed":2.07,"Feels_Like":273.73,"Temp":275.82,"Temp_max":278.64,"Temp_min":275.82,"Data":"2022-01-20 21:00:00"}},{"Main":{"Speed":1.8,"Feels_Like":274.85,"Temp":276.52,"Temp_max":277.93,"Temp_min":276.52,"Data":"2022-01-21 00:00:00"}},{"Main":{"Speed":2.85,"Feels_Like":274.18,"Temp":276.82,"Temp_max":277.32,"Temp_min":276.82,"Data":"2022-01-21 03:00:00"}},{"Main":{"Speed":5.19,"Feels_Like":272.8,"Temp":276.88,"Temp_max":276.88,"Temp_min":276.88,"Data":"2022-01-21 06:00:00"}},{"Main":{"Speed":6.25,"Feels_Like":274.31,"Temp":278.44,"Temp_max":278.44,"Temp_min":278.44,"Data":"2022-01-21 09:00:00"}},{"Main":{"Speed":5.86,"Feels_Like":276.87,"Temp":280.33,"Temp_max":280.33,"Temp_min":280.33,"Data":"2022-01-21 12:00:00"}},{"Main":{"Speed":2.97,"Feels_Like":277.85,"Temp":279.96,"Temp_max":279.96,"Temp_min":279.96,"Data":"2022-01-21 15:00:00"}},{"Main":{"Speed":2.61,"Feels_Like":276.22,"Temp":278.37,"Temp_max":278.37,"Temp_min":278.37,"Data":"2022-01-21 18:00:00"}},{"Main":{"Speed":2.15,"Feels_Like":275.33,"Temp":277.26,"Temp_max":277.26,"Temp_min":277.26,"Data":"2022-01-21 21:00:00"}},{"Main":{"Speed":1.67,"Feels_Like":275.13,"Temp":276.62,"Temp_max":276.62,"Temp_min":276.62,"Data":"2022-01-22 00:00:00"}},{"Main":{"Speed":2.05,"Feels_Like":273.64,"Temp":275.73,"Temp_max":275.73,"Temp_min":275.73,"Data":"2022-01-22 03:00:00"}},{"Main":{"Speed":1.37,"Feels_Like":274.01,"Temp":275.27,"Temp_max":275.27,"Temp_min":275.27,"Data":"2022-01-22 06:00:00"}},{"Main":{"Speed":3.11,"Feels_Like":274.07,"Temp":276.9,"Temp_max":276.9,"Temp_min":276.9,"Data":"2022-01-22 09:00:00"}},{"Main":{"Speed":3.24,"Feels_Like":276.52,"Temp":279.01,"Temp_max":279.01,"Temp_min":279.01,"Data":"2022-01-22 12:00:00"}},{"Main":{"Speed":1.12,"Feels_Like":279.08,"Temp":279.08,"Temp_max":279.08,"Temp_min":279.08,"Data":"2022-01-22 15:00:00"}},{"Main":{"Speed":1.76,"Feels_Like":275.91,"Temp":277.4,"Temp_max":277.4,"Temp_min":277.4,"Data":"2022-01-22 18:00:00"}},{"Main":{"Speed":2.1,"Feels_Like":274.8,"Temp":276.77,"Temp_max":276.77,"Temp_min":276.77,"Data":"2022-01-22 21:00:00"}},{"Main":{"Speed":2.36,"Feels_Like":273.85,"Temp":276.18,"Temp_max":276.18,"Temp_min":276.18,"Data":"2022-01-23 00:00:00"}},{"Main":{"Speed":1.98,"Feels_Like":273.86,"Temp":275.85,"Temp_max":275.85,"Temp_min":275.85,"Data":"2022-01-23 03:00:00"}},{"Main":{"Speed":1.99,"Feels_Like":273.86,"Temp":275.86,"Temp_max":275.86,"Temp_min":275.86,"Data":"2022-01-23 06:00:00"}},{"Main":{"Speed":1.67,"Feels_Like":275.75,"Temp":277.16,"Temp_max":277.16,"Temp_min":277.16,"Data":"2022-01-23 09:00:00"}},{"Main":{"Speed":0.67,"Feels_Like":279.29,"Temp":279.29,"Temp_max":279.29,"Temp_min":279.29,"Data":"2022-01-23 12:00:00"}},{"Main":{"Speed":0.63,"Feels_Like":279.54,"Temp":279.54,"Temp_max":279.54,"Temp_min":279.54,"Data":"2022-01-23 15:00:00"}},{"Main":{"Speed":1.51,"Feels_Like":277.05,"Temp":278.12,"Temp_max":278.12,"Temp_min":278.12,"Data":"2022-01-23 18:00:00"}},{"Main":{"Speed":1.83,"Feels_Like":275.97,"Temp":277.52,"Temp_max":277.52,"Temp_min":277.52,"Data":"2022-01-23 21:00:00"}},{"Main":{"Speed":1.35,"Feels_Like":276.22,"Temp":277.19,"Temp_max":277.19,"Temp_min":277.19,"Data":"2022-01-24 00:00:00"}},{"Main":{"Speed":1.55,"Feels_Like":275.61,"Temp":276.91,"Temp_max":276.91,"Temp_min":276.91,"Data":"2022-01-24 03:00:00"}},{"Main":{"Speed":2.45,"Feels_Like":274.01,"Temp":276.39,"Temp_max":276.39,"Temp_min":276.39,"Data":"2022-01-24 06:00:00"}},{"Main":{"Speed":2.38,"Feels_Like":275.8,"Temp":277.85,"Temp_max":277.85,"Temp_min":277.85,"Data":"2022-01-24 09:00:00"}},{"Main":{"Speed":1.47,"Feels_Like":279.39,"Temp":280.13,"Temp_max":280.13,"Temp_min":280.13,"Data":"2022-01-24 12:00:00"}},{"Main":{"Speed":0.54,"Feels_Like":280.38,"Temp":280.38,"Temp_max":280.38,"Temp_min":280.38,"Data":"2022-01-24 15:00:00"}},{"Main":{"Speed":0.23,"Feels_Like":279.86,"Temp":279.86,"Temp_max":279.86,"Temp_min":279.86,"Data":"2022-01-24 18:00:00"}},{"Main":{"Speed":1.18,"Feels_Like":279.41,"Temp":279.41,"Temp_max":279.41,"Temp_min":279.41,"Data":"2022-01-24 21:00:00"}},{"Main":{"Speed":1.81,"Feels_Like":277.66,"Temp":278.96,"Temp_max":278.96,"Temp_min":278.96,"Data":"2022-01-25 00:00:00"}},{"Main":{"Speed":2.16,"Feels_Like":276.89,"Temp":278.6,"Temp_max":278.6,"Temp_min":278.6,"Data":"2022-01-25 03:00:00"}},{"Main":{"Speed":2.38,"Feels_Like":276.46,"Temp":278.41,"Temp_max":278.41,"Temp_min":278.41,"Data":"2022-01-25 06:00:00"}},{"Main":{"Speed":1.3,"Feels_Like":278.75,"Temp":278.75,"Temp_max":278.75,"Temp_min":278.75,"Data":"2022-01-25 09:00:00"}},{"Main":{"Speed":1.63,"Feels_Like":279.23,"Temp":280.15,"Temp_max":280.15,"Temp_min":280.15,"Data":"2022-01-25 12:00:00"}},{"Main":{"Speed":2.18,"Feels_Like":279.31,"Temp":280.68,"Temp_max":280.68,"Temp_min":280.68,"Data":"2022-01-25 15:00:00"}},{"Main":{"Speed":2.59,"Feels_Like":277.1,"Temp":279.1,"Temp_max":279.1,"Temp_min":279.1,"Data":"2022-01-25 18:00:00"}}],"Name":"Venice"}
{"Id":3164603,"JSON-DATI ":[{"Main":{"Speed":2.07,"Feels_Like":273.73,"Temp":275.82,"Temp_max":278.64,"Temp_min":275.82,"Data":"2022-01-20 21:00:00"}},{"Main":{"Speed":1.8,"Feels_Like":274.85,"Temp":276.52,"Temp_max":277.93,"Temp_min":276.52,"Data":"2022-01-21 00:00:00"}},{"Main":{"Speed":2.85,"Feels_Like":274.18,"Temp":276.82,"Temp_max":277.32,"Temp_min":276.82,"Data":"2022-01-21 03:00:00"}},{"Main":{"Speed":5.19,"Feels_Like":272.8,"Temp":276.88,"Temp_max":276.88,"Temp_min":276.88,"Data":"2022-01-21 06:00:00"}},{"Main":{"Speed":6.25,"Feels_Like":274.31,"Temp":278.44,"Temp_max":278.44,"Temp_min":278.44,"Data":"2022-01-21 09:00:00"}},{"Main":{"Speed":5.86,"Feels_Like":276.87,"Temp":280.33,"Temp_max":280.33,"Temp_min":280.33,"Data":"2022-01-21 12:00:00"}},{"Main":{"Speed":2.97,"Feels_Like":277.85,"Temp":279.96,"Temp_max":279.96,"Temp_min":279.96,"Data":"2022-01-21 15:00:00"}},{"Main":{"Speed":2.61,"Feels_Like":276.22,"Temp":278.37,"Temp_max":278.37,"Temp_min":278.37,"Data":"2022-01-21 18:00:00"}},{"Main":{"Speed":2.15,"Feels_Like":275.33,"Temp":277.26,"Temp_max":277.26,"Temp_min":277.26,"Data":"2022-01-21 21:00:00"}},{"Main":{"Speed":1.67,"Feels_Like":275.13,"Temp":276.62,"Temp_max":276.62,"Temp_min":276.62,"Data":"2022-01-22 00:00:00"}},{"Main":{"Speed":2.05,"Feels_Like":273.64,"Temp":275.73,"Temp_max":275.73,"Temp_min":275.73,"Data":"2022-01-22 03:00:00"}},{"Main":{"Speed":1.37,"Feels_Like":274.01,"Temp":275.27,"Temp_max":275.27,"Temp_min":275.27,"Data":"2022-01-22 06:00:00"}},{"Main":{"Speed":3.11,"Feels_Like":274.07,"Temp":276.9,"Temp_max":276.9,"Temp_min":276.9,"Data":"2022-01-22 09:00:00"}},{"Main":{"Speed":3.24,"Feels_Like":276.52,"Temp":279.01,"Temp_max":279.01,"Temp_min":279.01,"Data":"2022-01-22 12:00:00"}},{"Main":{"Speed":1.12,"Feels_Like":279.08,"Temp":279.08,"Temp_max":279.08,"Temp_min":279.08,"Data":"2022-01-22 15:00:00"}},{"Main":{"Speed":1.76,"Feels_Like":275.91,"Temp":277.4,"Temp_max":277.4,"Temp_min":277.4,"Data":"2022-01-22 18:00:00"}},{"Main":{"Speed":2.1,"Feels_Like":274.8,"Temp":276.77,"Temp_max":276.77,"Temp_min":276.77,"Data":"2022-01-22 21:00:00"}},{"Main":{"Speed":2.36,"Feels_Like":273.85,"Temp":276.18,"Temp_max":276.18,"Temp_min":276.18,"Data":"2022-01-23 00:00:00"}},{"Main":{"Speed":1.98,"Feels_Like":273.86,"Temp":275.85,"Temp_max":275.85,"Temp_min":275.85,"Data":"2022-01-23 03:00:00"}},{"Main":{"Speed":1.99,"Feels_Like":273.86,"Temp":275.86,"Temp_max":275.86,"Temp_min":275.86,"Data":"2022-01-23 06:00:00"}},{"Main":{"Speed":1.67,"Feels_Like":275.75,"Temp":277.16,"Temp_max":277.16,"Temp_min":277.16,"Data":"2022-01-23 09:00:00"}},{"Main":{"Speed":0.67,"Feels_Like":279.29,"Temp":279.29,"Temp_max":279.29,"Temp_min":279.29,"Data":"2022-01-23 12:00:00"}},{"Main":{"Speed":0.63,"Feels_Like":279.54,"Temp":279.54,"Temp_max":279.54,"Temp_min":279.54,"Data":"2022-01-23 15:00:00"}},{"Main":{"Speed":1.51,"Feels_Like":277.05,"Temp":278.12,"Temp_max":278.12,"Temp_min":278.12,"Data":"2022-01-23 18:00:00"}},{"Main":{"Speed":1.83,"Feels_Like":275.97,"Temp":277.52,"Temp_max":277.52,"Temp_min":277.52,"Data":"2022-01-23 21:00:00"}},{"Main":{"Speed":1.35,"Feels_Like":276.22,"Temp":277.19,"Temp_max":277.19,"Temp_min":277.19,"Data":"2022-01-24 00:00:00"}},{"Main":{"Speed":1.55,"Feels_Like":275.61,"Temp":276.91,"Temp_max":276.91,"Temp_min":276.91,"Data":"2022-01-24 03:00:00"}},{"Main":{"Speed":2.45,"Feels_Like":274.01,"Temp":276.39,"Temp_max":276.39,"Temp_min":276.39,"Data":"2022-01-24 06:00:00"}},{"Main":{"Speed":2.38,"Feels_Like":275.8,"Temp":277.85,"Temp_max":277.85,"Temp_min":277.85,"Data":"2022-01-24 09:00:00"}},{"Main":{"Speed":1.47,"Feels_Like":279.39,"Temp":280.13,"Temp_max":280.13,"Temp_min":280.13,"Data":"2022-01-24 12:00:00"}},{"Main":{"Speed":0.54,"Feels_Like":280.38,"Temp":280.38,"Temp_max":280.38,"Temp_min":280.38,"Data":"2022-01-24 15:00:00"}},{"Main":{"Speed":0.23,"Feels_Like":279.86,"Temp":279.86,"Temp_max":279.86,"Temp_min":279.86,"Data":"2022-01-24 18:00:00"}},{"Main":{"Speed":1.18,"Feels_Like":279.41,"Temp":279.41,"Temp_max":279.41,"Temp_min":279.41,"Data":"2022-01-24 21:00:00"}},{"Main":{"Speed":1.81,"Feels_Like":277.66,"Temp":278.96,"Temp_max":278.96,"Temp_min":278.96,"Data":"2022-01-25 00:00:00"}},{"Main":{"Speed":2.16,"Feels_Like":276.89,"Temp":278.6,"Temp_max":278.6,"Temp_min":278.6,"Data":"2022-01-25 03:00:00"}},{"Main":{"Speed":2.38,"Feels_Like":276.46,"Temp":278.41,"Temp_max":278.41,"Temp_min":278.41,"Data":"2022-01-25 06:00:00"}},{"Main":{"Speed":1.3,"Feels_Like":278.75,"Temp":278.75,"Temp_max":278.75,"Temp_min":278.75,"Data":"2022-01-25 09:00:00"}},{"Main":{"Speed":1.63,"Feels_Like":279.23,"Temp":280.15,"Temp_max":280.15,"Temp_min":280.15,"Data":"2022-01-25 12:00:00"}},{"Main":{"Speed":2.18,"Feels_Like":279.31,"Temp":280.68,"Temp_max":280.68,"Temp_min":280.68,"Data":"2022-01-25 15:00:00"}},{"Main":{"Speed":2.59,"Feels_Like":277.1,"Temp":279.1,"Temp_max":279.1,"Temp_min":279.1,"Data":"2022-01-25 18:00:00"}}],"Name":"Venice"}
{"Id":3164603,"JSON-DATI ":[{"Main":{"Speed":2.07,"Feels_Like":273.73,"Temp":275.82,"Temp_max":278.64,"Temp_min":275.82,"Data":"2022-01-20 21:00:00"}},{"Main":{"Speed":1.8,"Feels_Like":274.85,"Temp":276.52,"Temp_max":277.93,"Temp_min":276.52,"Data":"2022-01-21 00:00:00"}},{"Main":{"Speed":2.85,"Feels_Like":274.18,"Temp":276.82,"Temp_max":277.32,"Temp_min":276.82,"Data":"2022-01-21 03:00:00"}},{"Main":{"Speed":5.19,"Feels_Like":272.8,"Temp":276.88,"Temp_max":276.88,"Temp_min":276.88,"Data":"2022-01-21 06:00:00"}},{"Main":{"Speed":6.25,"Feels_Like":274.31,"Temp":278.44,"Temp_max":278.44,"Temp_min":278.44,"Data":"2022-01-21 09:00:00"}},{"Main":{"Speed":5.86,"Feels_Like":276.87,"Temp":280.33,"Temp_max":280.33,"Temp_min":280.33,"Data":"2022-01-21 12:00:00"}},{"Main":{"Speed":2.97,"Feels_Like":277.85,"Temp":279.96,"Temp_max":279.96,"Temp_min":279.96,"Data":"2022-01-21 15:00:00"}},{"Main":{"Speed":2.61,"Feels_Like":276.22,"Temp":278.37,"Temp_max":278.37,"Temp_min":278.37,"Data":"2022-01-21 18:00:00"}},{"Main":{"Speed":2.15,"Feels_Like":275.33,"Temp":277.26,"Temp_max":277.26,"Temp_min":277.26,"Data":"2022-01-21 21:00:00"}},{"Main":{"Speed":1.67,"Feels_Like":275.13,"Temp":276.62,"Temp_max":276.62,"Temp_min":276.62,"Data":"2022-01-22 00:00:00"}},{"Main":{"Speed":2.05,"Feels_Like":273.64,"Temp":275.73,"Temp_max":275.73,"Temp_min":275.73,"Data":"2022-01-22 03:00:00"}},{"Main":{"Speed":1.37,"Feels_Like":274.01,"Temp":275.27,"Temp_max":275.27,"Temp_min":275.27,"Data":"2022-01-22 06:00:00"}},{"Main":{"Speed":3.11,"Feels_Like":274.07,"Temp":276.9,"Temp_max":276.9,"Temp_min":276.9,"Data":"2022-01-22 09:00:00"}},{"Main":{"Speed":3.24,"Feels_Like":276.52,"Temp":279.01,"Temp_max":279.01,"Temp_min":279.01,"Data":"2022-01-22 12:00:00"}},{"Main":{"Speed":1.12,"Feels_Like":279.08,"Temp":279.08,"Temp_max":279.08,"Temp_min":279.08,"Data":"2022-01-22 15:00:00"}},{"Main":{"Speed":1.76,"Feels_Like":275.91,"Temp":277.4,"Temp_max":277.4,"Temp_min":277.4,"Data":"2022-01-22 18:00:00"}},{"Main":{"Speed":2.1,"Feels_Like":274.8,"Temp":276.77,"Temp_max":276.77,"Temp_min":276.77,"Data":"2022-01-22 21:00:00"}},{"Main":{"Speed":2.36,"Feels_Like":273.85,"Temp":276.18,"Temp_max":276.18,"Temp_min":276.18,"Data":"2022-01-23 00:00:00"}},{"Main":{"Speed":1.98,"Feels_Like":273.86,"Temp":275.85,"Temp_max":275.85,"Temp_min":275.85,"Data":"2022-01-23 03:00:00"}},{"Main":{"Speed":1.99,"Feels_Like":273.86,"Temp":275.86,"Temp_max":275.86,"Temp_min":275.86,"Data":"2022-01-23 06:00:00"}},{"Main":{"Speed":1.67,"Feels_Like":275.75,"Temp":277.16,"Temp_max":277.16,"Temp_min":277.16,"Data":"2022-01-23 09:00:00"}},{"Main":{"Speed":0.67,"Feels_Like":279.29,"Temp":279.29,"Temp_max":279.29,"Temp_min":279.29,"Data":"2022-01-23 12:00:00"}},{"Main":{"Speed":0.63,"Feels_Like":279.54,"Temp":279.54,"Temp_max":279.54,"Temp_min":279.54,"Data":"2022-01-23 15:00:00"}},{"Main":{"Speed":1.51,"Feels_Like":277.05,"Temp":278.12,"Temp_max":278.12,"Temp_min":278.12,"Data":"2022-01-23 18:00:00"}},{"Main":{"Speed":1.83,"Feels_Like":275.97,"Temp":277.52,"Temp_max":277.52,"Temp_min":277.52,"Data":"2022-01-23 21:00:00"}},{"Main":{"Speed":1.35,"Feels_Like":276.22,"Temp":277.19,"Temp_max":277.19,"Temp_min":277.19,"Data":"2022-01-24 00:00:00"}},{"Main":{"Speed":1.55,"Feels_Like":275.61,"Temp":276.91,"Temp_max":276.91,"Temp_min":276.91,"Data":"2022-01-24 03:00:00"}},{"Main":{"Speed":2.45,"Feels_Like":274.01,"Temp":276.39,"Temp_max":276.39,"Temp_min":276.39,"Data":"2022-01-24 06:00:00"}},{"Main":{"Speed":2.38,"Feels_Like":275.8,"Temp":277.85,"Temp_max":277.85,"Temp_min":277.85,"Data":"2022-01-24 09:00:00"}},{"Main":{"Speed":1.47,"Feels_Like":279.39,"Temp":280.13,"Temp_max":280.13,"Temp_min":280.13,"Data":"2022-01-24 12:00:00"}},{"Main":{"Speed":0.54,"Feels_Like":280.38,"Temp":280.38,"Temp_max":280.38,"Temp_min":280.38,"Data":"2022-01-24 15:00:00"}},{"Main":{"Speed":0.23,"Feels_Like":279.86,"Temp":279.86,"Temp_max":279.86,"Temp_min":279.86,"Data":"2022-01-24 18:00:00"}},{"Main":{"Speed":1.18,"Feels_Like":279.41,"Temp":279.41,"Temp_max":279.41,"Temp_min":279.41,"Data":"2022-01-24 21:00:00"}},{"Main":{"Speed":1.81,"Feels_Like":277.66,"Temp":278.96,"Temp_max":278.96,"Temp_min":278.96,"Data":"2022-01-25 00:00:00"}},{"Main":{"Speed":2.16,"Feels_Like":276.89,"Temp":278.6,"Temp_max":278.6,"Temp_min":278.6,"Data":"2022-01-25 03:00:00"}},{"Main":{"Speed":2.38,"Feels_Like":276.46,"Temp":278.41,"Temp_max":278.41,"Temp_min":278.41,"Data":"2022-01-25 06:00:00"}},{"Main":{"Speed":1.3,"Feels_Like":278.75,"Temp":278.75,"Temp_max":278.75,"Temp_min":278.75,"Data":"2022-01-25 09:00:00"}},{"Main":{"Speed":1.63,"Feels_Like":279.23,"Temp":280.15,"Temp_max":280.15,"Temp_min":280.15,"Data":"2022-01-25 12:00:00"}},{"Main":{"Speed":2.18,"Feels_Like":279.31,"Temp":280.68,"Temp_max":280.68,"Temp_min":280.68,"Data":"2022-01-25 15:00:00"}},{"Main":{"Speed":2.59,"Feels_Like":277.1,"Temp":279.1,"Temp_max":279.1,"Temp_min":279.1,"Data":"2022-01-25 18:00:00"}}],"Name":"Venice"}
{"Id":3164603,"JSON-DATI ":[{"Main":{"Speed":2.07,"Feels_Like":273.73,"Temp":275.82,"Temp_max":278.64,"Temp_min":275.82,"Data":"2022-01-20 21:00:00"}},{"Main":{"Speed":1.8,"Feels_Like":274.85,"Temp":276.52,"Temp_max":277.93,"Temp_min":276.52,"Data":"2022-01-21 00:00:00"}},{"Main":{"Speed":2.85,"Feels_Like":274.18,"Temp":276.82,"Temp_max":277.32,"Temp_min":276.82,"Data":"2022-01-21 03:00:00"}},{"Main":{"Speed":5.19,"Feels_Like":272.8,"Temp":276.88,"Temp_max":276.88,"Temp_min":276.88,"Data":"2022-01-21 06:00:00"}},{"Main":{"Speed":6.25,"Feels_Like":274.31,"Temp":278.44,"Temp_max":278.44,"Temp_min":278.44,"Data":"2022-01-21 09:00:00"}},{"Main":{"Speed":5.86,"Feels_Like":276.87,"Temp":280.33,"Temp_max":280.33,"Temp_min":280.33,"Data":"2022-01-21 12:00:00"}},{"Main":{"Speed":2.97,"Feels_Like":277.85,"Temp":279.96,"Temp_max":279.96,"Temp_min":279.96,"Data":"2022-01-21 15:00:00"}},{"Main":{"Speed":2.61,"Feels_Like":276.22,"Temp":278.37,"Temp_max":278.37,"Temp_min":278.37,"Data":"2022-01-21 18:00:00"}},{"Main":{"Speed":2.15,"Feels_Like":275.33,"Temp":277.26,"Temp_max":277.26,"Temp_min":277.26,"Data":"2022-01-21 21:00:00"}},{"Main":{"Speed":1.67,"Feels_Like":275.13,"Temp":276.62,"Temp_max":276.62,"Temp_min":276.62,"Data":"2022-01-22 00:00:00"}},{"Main":{"Speed":2.05,"Feels_Like":273.64,"Temp":275.73,"Temp_max":275.73,"Temp_min":275.73,"Data":"2022-01-22 03:00:00"}},{"Main":{"Speed":1.37,"Feels_Like":274.01,"Temp":275.27,"Temp_max":275.27,"Temp_min":275.27,"Data":"2022-01-22 06:00:00"}},{"Main":{"Speed":3.11,"Feels_Like":274.07,"Temp":276.9,"Temp_max":276.9,"Temp_min":276.9,"Data":"2022-01-22 09:00:00"}},{"Main":{"Speed":3.24,"Feels_Like":276.52,"Temp":279.01,"Temp_max":279.01,"Temp_min":279.01,"Data":"2022-01-22 12:00:00"}},{"Main":{"Speed":1.12,"Feels_Like":279.08,"Temp":279.08,"Temp_max":279.08,"Temp_min":279.08,"Data":"2022-01-22 15:00:00"}},{"Main":{"Speed":1.76,"Feels_Like":275.91,"Temp":277.4,"Temp_max":277.4,"Temp_min":277.4,"Data":"2022-01-22 18:00:00"}},{"Main":{"Speed":2.1,"Feels_Like":274.8,"Temp":276.77,"Temp_max":276.77,"Temp_min":276.77,"Data":"2022-01-22 21:00:00"}},{"Main":{"Speed":2.36,"Feels_Like":273.85,"Temp":276.18,"Temp_max":276.18,"Temp_min":276.18,"Data":"2022-01-23 00:00:00"}},{"Main":{"Speed":1.98,"Feels_Like":273.86,"Temp":275.85,"Temp_max":275.85,"Temp_min":275.85,"Data":"2022-01-23 03:00:00"}},{"Main":{"Speed":1.99,"Feels_Like":273.86,"Temp":275.86,"Temp_max":275.86,"Temp_min":275.86,"Data":"2022-01-23 06:00:00"}},{"Main":{"Speed":1.67,"Feels_Like":275.75,"Temp":277.16,"Temp_max":277.16,"Temp_min":277.16,"Data":"2022-01-23 09:00:00"}},{"Main":{"Speed":0.67,"Feels_Like":279.29,"Temp":279.29,"Temp_max":279.29,"Temp_min":279.29,"Data":"2022-01-23 12:00:00"}},{"Main":{"Speed":0.63,"Feels_Like":279.54,"Temp":279.54,"Temp_max":279.54,"Temp_min":279.54,"Data":"2022-01-23 15:00:00"}},{"Main":{"Speed":1.51,"Feels_Like":277.05,"Temp":278.12,"Temp_max":278.12,"Temp_min":278.12,"Data":"2022-01-23 18:00:00"}},{"Main":{"Speed":1.83,"Feels_Like":275.97,"Temp":277.52,"Temp_max":277.52,"Temp_min":277.52,"Data":"2022-01-23 21:00:00"}},{"Main":{"Speed":1.35,"Feels_Like":276.22,"Temp":277.19,"Temp_max":277.19,"Temp_min":277.19,"Data":"2022-01-24 00:00:00"}},{"Main":{"Speed":1.55,"Feels_Like":275.61,"Temp":276.91,"Temp_max":276.91,"Temp_min":276.91,"Data":"2022-01-24 03:00:00"}},{"Main":{"Speed":2.45,"Feels_Like":274.01,"Temp":276.39,"Temp_max":276.39,"Temp_min":276.39,"Data":"2022-01-24 06:00:00"}},{"Main":{"Speed":2.38,"Feels_Like":275.8,"Temp":277.85,"Temp_max":277.85,"Temp_min":277.85,"Data":"2022-01-24 09:00:00"}},{"Main":{"Speed":1.47,"Feels_Like":279.39,"Temp":280.13,"Temp_max":280.13,"Temp_min":280.13,"Data":"2022-01-24 12:00:00"}},{"Main":{"Speed":0.54,"Feels_Like":280.38,"Temp":280.38,"Temp_max":280.38,"Temp_min":280.38,"Data":"2022-01-24 15:00:00"}},{"Main":{"Speed":0.23,"Feels_Like":279.86,"Temp":279.86,"Temp_max":279.86,"Temp_min":279.86,"Data":"2022-01-24 18:00:00"}},{"Main":{"Speed":1.18,"Feels_Like":279.41,"Temp":279.41,"Temp_max":279.41,"Temp_min":279.41,"Data":"2022-01-24 21:00:00"}},{"Main":{"Speed":1.81,"Feels_Like":277.66,"Temp":278.96,"Temp_max":278.96,"Temp_min":278.96,"Data":"2022-01-25 00:00:00"}},{"Main":{"Speed":2.16,"Feels_Like":276.89,"Temp":278.6,"Temp_max":278.6,"Temp_min":278.6,"Data":"2022-01-25 03:00:00"}},{"Main":{"Speed":2.38,"Feels_Like":276.46,"Temp":278.41,"Temp_max":278.41,"Temp_min":278.41,"Data":"2022-01-25 06:00:00"}},{"Main":{"Speed":1.3,"Feels_Like":278.75,"Temp":278.75,"Temp_max":278.75,"Temp_min":278.75,"Data":"2022-01-25 09:00:00"}},{"Main":{"Speed":1.63,"Feels_Like":279.23,"Temp":280.15,"Temp_max":280.15,"Temp_min":280.15,"Data":"2022-01-25 12:00:00"}},{"Main":{"Speed":2.18,"Feels_Like":279.31,"Temp":280.68,"Temp_max":280.68,"Temp_min":280.68,"Data":"2022-01-25 15:00:00"}},{"Main":{"Speed":2.59,"Feels_Like":277.1,"Temp":279.1,"Temp_max":279.1,"Temp_min":279.1,"Data":"2022-01-25 18:00:00"}}],"Name":"Venice"}
{"Id":3164603,"JSON-DATI ":[{"Main":{"Speed":2.07,"Feels_Like":273.73,"Temp":275.82,"Temp_max":278.64,"Temp_min":275.82,"Data":"2022-01-20 21:00:00"}},{"Main":{"Speed":1.8,"Feels_Like":274.85,"Temp":276.52,"Temp_max":277.93,"Temp_min":276.52,"Data":"2022-01-21 00:00:00"}},{"Main":{"Speed":2.85,"Feels_Like":274.18,"Temp":276.82,"Temp_max":277.32,"Temp_min":276.82,"Data":"2022-01-21 03:00:00"}},{"Main":{"Speed":5.19,"Feels_Like":272.8,"Temp":276.88,"Temp_max":276.88,"Temp_min":276.88,"Data":"2022-01-21 06:00:00"}},{"Main":{"Speed":6.25,"Feels_Like":274.31,"Temp":278.44,"Temp_max":278.44,"Temp_min":278.44,"Data":"2022-01-21 09:00:00"}},{"Main":{"Speed":5.86,"Feels_Like":276.87,"Temp":280.33,"Temp_max":280.33,"Temp_min":280.33,"Data":"2022-01-21 12:00:00"}},{"Main":{"Speed":2.97,"Feels_Like":277.85,"Temp":279.96,"Temp_max":279.96,"Temp_min":279.96,"Data":"2022-01-21 15:00:00"}},{"Main":{"Speed":2.61,"Feels_Like":276.22,"Temp":278.37,"Temp_max":278.37,"Temp_min":278.37,"Data":"2022-01-21 18:00:00"}},{"Main":{"Speed":2.15,"Feels_Like":275.33,"Temp":277.26,"Temp_max":277.26,"Temp_min":277.26,"Data":"2022-01-21 21:00:00"}},{"Main":{"Speed":1.67,"Feels_Like":275.13,"Temp":276.62,"Temp_max":276.62,"Temp_min":276.62,"Data":"2022-01-22 00:00:00"}},{"Main":{"Speed":2.05,"Feels_Like":273.64,"Temp":275.73,"Temp_max":275.73,"Temp_min":275.73,"Data":"2022-01-22 03:00:00"}},{"Main":{"Speed":1.37,"Feels_Like":274.01,"Temp":275.27,"Temp_max":275.27,"Temp_min":275.27,"Data":"2022-01-22 06:00:00"}},{"Main":{"Speed":3.11,"Feels_Like":274.07,"Temp":276.9,"Temp_max":276.9,"Temp_min":276.9,"Data":"2022-01-22 09:00:00"}},{"Main":{"Speed":3.24,"Feels_Like":276.52,"Temp":279.01,"Temp_max":279.01,"Temp_min":279.01,"Data":"2022-01-22 12:00:00"}},{"Main":{"Speed":1.12,"Feels_Like":279.08,"Temp":279.08,"Temp_max":279.08,"Temp_min":279.08,"Data":"2022-01-22 15:00:00"}},{"Main":{"Speed":1.76,"Feels_Like":275.91,"Temp":277.4,"Temp_max":277.4,"Temp_min":277.4,"Data":"2022-01-22 18:00:00"}},{"Main":{"Speed":2.1,"Feels_Like":274.8,"Temp":276.77,"Temp_max":276.77,"Temp_min":276.77,"Data":"2022-01-22 21:00:00"}},{"Main":{"Speed":2.36,"Feels_Like":273.85,"Temp":276.18,"Temp_max":276.18,"Temp_min":276.18,"Data":"2022-01-23 00:00:00"}},{"Main":{"Speed":1.98,"Feels_Like":273.86,"Temp":275.85,"Temp_max":275.85,"Temp_min":275.85,"Data":"2022-01-23 03:00:00"}},{"Main":{"Speed":1.99,"Feels_Like":273.86,"Temp":275.86,"Temp_max":275.86,"Temp_min":275.86,"Data":"2022-01-23 06:00:00"}},{"Main":{"Speed":1.67,"Feels_Like":275.75,"Temp":277.16,"Temp_max":277.16,"Temp_min":277.16,"Data":"2022-01-23 09:00:00"}},{"Main":{"Speed":0.67,"Feels_Like":279.29,"Temp":279.29,"Temp_max":279.29,"Temp_min":279.29,"Data":"2022-01-23 12:00:00"}},{"Main":{"Speed":0.63,"Feels_Like":279.54,"Temp":279.54,"Temp_max":279.54,"Temp_min":279.54,"Data":"2022-01-23 15:00:00"}},{"Main":{"Speed":1.51,"Feels_Like":277.05,"Temp":278.12,"Temp_max":278.12,"Temp_min":278.12,"Data":"2022-01-23 18:00:00"}},{"Main":{"Speed":1.83,"Feels_Like":275.97,"Temp":277.52,"Temp_max":277.52,"Temp_min":277.52,"Data":"2022-01-23 21:00:00"}},{"Main":{"Speed":1.35,"Feels_Like":276.22,"Temp":277.19,"Temp_max":277.19,"Temp_min":277.19,"Data":"2022-01-24 00:00:00"}},{"Main":{"Speed":1.55,"Feels_Like":275.61,"Temp":276.91,"Temp_max":276.91,"Temp_min":276.91,"Data":"2022-01-24 03:00:00"}},{"Main":{"Speed":2.45,"Feels_Like":274.01,"Temp":276.39,"Temp_max":276.39,"Temp_min":276.39,"Data":"2022-01-24 06:00:00"}},{"Main":{"Speed":2.38,"Feels_Like":275.8,"Temp":277.85,"Temp_max":277.85,"Temp_min":277.85,"Data":"2022-01-24 09:00:00"}},{"Main":{"Speed":1.47,"Feels_Like":279.39,"Temp":280.13,"Temp_max":280.13,"Temp_min":280.13,"Data":"2022-01-24 12:00:00"}},{"Main":{"Speed":0.54,"Feels_Like":280.38,"Temp":280.38,"Temp_max":280.38,"Temp_min":280.38,"Data":"2022-01-24 15:00:00"}},{"Main":{"Speed":0.23,"Feels_Like":279.86,"Temp":279.86,"Temp_max":279.86,"Temp_min":279.86,"Data":"2022-01-24 18:00:00"}},{"Main":{"Speed":1.18,"Feels_Like":279.41,"Temp":279.41,"Temp_max":279.41,"Temp_min":279.41,"Data":"2022-01-24 21:00:00"}},{"Main":{"Speed":1.81,"Feels_Like":277.66,"Temp":278.96,"Temp_max":278.96,"Temp_min":278.96,"Data":"2022-01-25 00:00:00"}},{"Main":{"Speed":2.16,"Feels_Like":276.89,"Temp":278.6,"Temp_max":278.6,"Temp_min":278.6,"Data":"2022-01-25 03:00:00"}},{"Main":{"Speed":2.38,"Feels_Like":276.46,"Temp":278.41,"Temp_max":278.41,"Temp_min":278.41,"Data":"2022-01-25 06:00:00"}},{"Main":{"Speed":1.3,"Feels_Like":278.75,"Temp":278.75,"Temp_max":278.75,"Temp_min":278.75,"Data":"2022-01-25 09:00:00"}},{"Main":{"Speed":1.63,"Feels_Like":279.23,"Temp":280.15,"Temp_max":280.15,"Temp_min":280.15,"Data":"2022-01-25 12:00:00"}},{"Main":{"Speed":2.18,"Feels_Like":279.31,"Temp":280.68,"Temp_max":280.68,"Temp_min":280.68,"Data":"2022-01-25 15:00:00"}},{"Main":{"Speed":2.59,"Feels_Like":277.1,"Temp":279.1,"Temp_max":279.1,"Temp_min":279.1,"Data":"2022-01-25 18:00:00"}}],"Name":"Venice"}
{"Id":3164603,"JSON-DATI ":[{"Main":{"Speed":2.07,"Feels_Like":273.73,"Temp":275.82,"Temp_max":278.64,"Temp_min":275.82,"Data":"2022-01-20 21:00:00"}},{"Main":{"Speed":1.8,"Feels_Like":274.85,"Temp":276.52,"Temp_max":277.93,"Temp_min":276.52,"Data":"2022-01-21 00:00:00"}},{"Main":{"Speed":2.85,"Feels_Like":274.18,"Temp":276.82,"Temp_max":277.32,"Temp_min":276.82,"Data":"2022-01-21 03:00:00"}},{"Main":{"Speed":5.19,"Feels_Like":272.8,"Temp":276.88,"Temp_max":276.88,"Temp_min":276.88,"Data":"2022-01-21 06:00:00"}},{"Main":{"Speed":6.25,"Feels_Like":274.31,"Temp":278.44,"Temp_max":278.44,"Temp_min":278.44,"Data":"2022-01-21 09:00:00"}},{"Main":{"Speed":5.86,"Feels_Like":276.87,"Temp":280.33,"Temp_max":280.33,"Temp_min":280.33,"Data":"2022-01-21 12:00:00"}},{"Main":{"Speed":2.97,"Feels_Like":277.85,"Temp":279.96,"Temp_max":279.96,"Temp_min":279.96,"Data":"2022-01-21 15:00:00"}},{"Main":{"Speed":2.61,"Feels_Like":276.22,"Temp":278.37,"Temp_max":278.37,"Temp_min":278.37,"Data":"2022-01-21 18:00:00"}},{"Main":{"Speed":2.15,"Feels_Like":275.33,"Temp":277.26,"Temp_max":277.26,"Temp_min":277.26,"Data":"2022-01-21 21:00:00"}},{"Main":{"Speed":1.67,"Feels_Like":275.13,"Temp":276.62,"Temp_max":276.62,"Temp_min":276.62,"Data":"2022-01-22 00:00:00"}},{"Main":{"Speed":2.05,"Feels_Like":273.64,"Temp":275.73,"Temp_max":275.73,"Temp_min":275.73,"Data":"2022-01-22 03:00:00"}},{"Main":{"Speed":1.37,"Feels_Like":274.01,"Temp":275.27,"Temp_max":275.27,"Temp_min":275.27,"Data":"2022-01-22 06:00:00"}},{"Main":{"Speed":3.11,"Feels_Like":274.07,"Temp":276.9,"Temp_max":276.9,"Temp_min":276.9,"Data":"2022-01-22 09:00:00"}},{"Main":{"Speed":3.24,"Feels_Like":276.52,"Temp":279.01,"Temp_max":279.01,"Temp_min":279.01,"Data":"2022-01-22 12:00:00"}},{"Main":{"Speed":1.12,"Feels_Like":279.08,"Temp":279.08,"Temp_max":279.08,"Temp_min":279.08,"Data":"2022-01-22 15:00:00"}},{"Main":{"Speed":1.76,"Feels_Like":275.91,"Temp":277.4,"Temp_max":277.4,"Temp_min":277.4,"Data":"2022-01-22 18:00:00"}},{"Main":{"Speed":2.1,"Feels_Like":274.8,"Temp":276.77,"Temp_max":276.77,"Temp_min":276.77,"Data":"2022-01-22 21:00:00"}},{"Main":{"Speed":2.36,"Feels_Like":273.85,"Temp":276.18,"Temp_max":276.18,"Temp_min":276.18,"Data":"2022-01-23 00:00:00"}},{"Main":{"Speed":1.98,"Feels_Like":273.86,"Temp":275.85,"Temp_max":275.85,"Temp_min":275.85,"Data":"2022-01-23 03:00:00"}},{"Main":{"Speed":1.99,"Feels_Like":273.86,"Temp":275.86,"Temp_max":275.86,"Temp_min":275.86,"Data":"2022-01-23 06:00:00"}},{"Main":{"Speed":1.67,"Feels_Like":275.75,"Temp":277.16,"Temp_max":277.16,"Temp_min":277.16,"Data":"2022-01-23 09:00:00"}},{"Main":{"Speed":0.67,"Feels_Like":279.29,"Temp":279.29,"Temp_max":279.29,"Temp_min":279.29,"Data":"2022-01-23 12:00:00"}},{"Main":{"Speed":0.63,"Feels_Like":279.54,"Temp":279.54,"Temp_max":279.54,"Temp_min":279.54,"Data":"2022-01-23 15:00:00"}},{"Main":{"Speed":1.51,"Feels_Like":277.05,"Temp":278.12,"Temp_max":278.12,"Temp_min":278.12,"Data":"2022-01-23 18:00:00"}},{"Main":{"Speed":1.83,"Feels_Like":275.97,"Temp":277.52,"Temp_max":277.52,"Temp_min":277.52,"Data":"2022-01-23 21:00:00"}},{"Main":{"Speed":1.35,"Feels_Like":276.22,"Temp":277.19,"Temp_max":277.19,"Temp_min":277.19,"Data":"2022-01-24 00:00:00"}},{"Main":{"Speed":1.55,"Feels_Like":275.61,"Temp":276.91,"Temp_max":276.91,"Temp_min":276.91,"Data":"2022-01-24 03:00:00"}},{"Main":{"Speed":2.45,"Feels_Like":274.01,"Temp":276.39,"Temp_max":276.39,"Temp_min":276.39,"Data":"2022-01-24 06:00:00"}},{"Main":{"Speed":2.38,"Feels_Like":275.8,"Temp":277.85,"Temp_max":277.85,"Temp_min":277.85,"Data":"2022-01-24 09:00:00"}},{"Main":{"Speed":1.47,"Feels_Like":279.39,"Temp":280.13,"Temp_max":280.13,"Temp_min":280.13,"Data":"2022-01-24 12:00:00"}},{"Main":{"Speed":0.54,"Feels_Like":280.38,"Temp":280.38,"Temp_max":280.38,"Temp_min":280.38,"Data":"2022-01-24 15:00:00"}},{"Main":{"Speed":0.23,"Feels_Like":279.86,"Temp":279.86,"Temp_max":279.86,"Temp_min":279.86,"Data":"2022-01-24 18:00:00"}},{"Main":{"Speed":1.18,"Feels_Like":279.41,"Temp":279.41,"Temp_max":279.41,"Temp_min":279.41,"Data":"2022-01-24 21:00:00"}},{"Main":{"Speed":1.81,"Feels_Like":277.66,"Temp":278.96,"Temp_max":278.96,"Temp_min":278.96,"Data":"2022-01-25 00:00:00"}},{"Main":{"Speed":2.16,"Feels_Like":276.89,"Temp":278.6,"Temp_max":278.6,"Temp_min":278.6,"Data":"2022-01-25 03:00:00"}},{"Main":{"Speed":2.38,"Feels_Like":276.46,"Temp":278.41,"Temp_max":278.41,"Temp_min":278.41,"Data":"2022-01-25 06:00:00"}},{"Main":{"Speed":1.3,"Feels_Like":278.75,"Temp":278.75,"Temp_max":278.75,"Temp_min":278.75,"Data":"2022-01-25 09:00:00"}},{"Main":{"Speed":1.63,"Feels_Like":279.23,"Temp":280.15,"Temp_max":280.15,"Temp_min":280.15,"Data":"2022-01-25 12:00:00"}},{"Main":{"Speed":2.18,"Feels_Like":279.31,"Temp":280.68,"Temp_max":280.68,"Temp_min":280.68,"Data":"2022-01-25 15:00:00"}},{"Main":{"Speed":2.59,"Feels_Like":277.1,"Temp":279.1,"Temp_max":279.1,"Temp_min":279.1,"Data":"2022-01-25 18:00:00"}}],"Name":"Venice"}
